{"cameraMode":{"drawMode":0,"name":"Shaded","section":"Shading Mode"},"sceneLighting":true,"audioPlay":false,"sceneViewState":{"m_AlwaysRefresh":false,"showFog":true,"showSkybox":true,"showFlares":true,"showImageEffects":true,"showParticleSystems":true,"showVisualEffectGraphs":true,"m_FxEnabled":true},"in2DMode":false,"pivot":{"x":-12.416010856628418,"y":-17.253040313720704,"z":23.665021896362306},"rotation":{"x":0.2932465970516205,"y":-0.1989039033651352,"z":0.062476757913827899,"w":0.9330697059631348},"size":21.82135009765625,"orthographic":false}