<Properties StartupConfiguration="{F13A0729-105A-7599-4420-7E58875361D8}|">
  <MonoDevelop.Ide.Workbench ActiveDocument="Assets/MainMenu.cs">
    <Files>
      <File FileName="Assets/MainMenu.cs" Line="14" Column="23" />
      <File FileName="Assets/GyroControl.cs" />
      <File FileName="Assets/EBackButtonScript.cs" />
      <File FileName="Assets/Game Contents/Earth/Scripts/SphereScript.cs" />
      <File FileName="Assets/pHPaperChange.cs" />
      <File FileName="Assets/Scenes/L2Vapours.cs" />
    </Files>
    <Pads>
      <Pad Id="ProjectPad">
        <State name="__root__">
          <Node name="EasyLabX" expanded="True">
            <Node name="Assets" expanded="True">
              <Node name="Game Contents" expanded="True">
                <Node name="Earth" expanded="True">
                  <Node name="Scripts" expanded="True" />
                </Node>
              </Node>
              <Node name="Scenes" expanded="True" />
              <Node name="MainMenu.cs" selected="True" />
            </Node>
          </Node>
        </State>
      </Pad>
    </Pads>
  </MonoDevelop.Ide.Workbench>
  <MonoDevelop.Ide.DebuggingService.PinnedWatches />
  <MonoDevelop.Ide.Workspace ActiveConfiguration="Debug" />
  <MonoDevelop.Ide.ItemProperties.Assembly-CSharp PreferredExecutionTarget="aa8341e5-a505-41ba-8777-b4d169e2b124" />
  <MonoDevelop.Ide.DebuggingService.Breakpoints>
    <BreakpointStore />
  </MonoDevelop.Ide.DebuggingService.Breakpoints>
  <MultiItemStartupConfigurations />
</Properties>